srndcipher.py
srndcipher-0.6.4.dist-info/licenses/LICENSE
srndcipher-0.6.4.dist-info/METADATA
srndcipher-0.6.4.dist-info/WHEEL
srndcipher-0.6.4.dist-info/top_level.txt
srndcipher-0.6.4.dist-info/RECORD
