Metadata-Version: 2.4
Name: srndcipher
Version: 0.6.4
Summary: A simple way to encode plain text, keeps the result sortable and partly searchable.
Author: rRR0VrFP
Maintainer: rRR0VrFP
License: MIT
Keywords: cipher,SrndCipher,result sortable and partly searchable
Classifier: Development Status :: 5 - Production/Stable
Classifier: Intended Audience :: Developers
Classifier: Topic :: Software Development :: Libraries :: Python Modules
Classifier: Programming Language :: Python :: 3
Classifier: Programming Language :: Python :: 3 :: Only
License-File: LICENSE
Requires-Dist: zenutils
Dynamic: author
Dynamic: classifier
Dynamic: description
Dynamic: description-content-type
Dynamic: keywords
Dynamic: license
Dynamic: license-file
Dynamic: maintainer
Dynamic: requires-dist
Dynamic: summary
